CHANGELOG.txt
LICENSE.txt
MANIFEST.in
README.txt
setup.py
dsdce/__init__.py
dsdce.egg-info/PKG-INFO
dsdce.egg-info/SOURCES.txt
dsdce.egg-info/dependency_links.txt
dsdce.egg-info/top_level.txt