Metadata-Version: 2.1
Name: dsdce
Version: 0.0.2
Summary: A simple library to get the code for all Data Structure tutorials for dce department PSG Polytechnic College. Developed by Mohamed Fazil, DCE Student, PSG Polytechnic College.
Home-page: UNKNOWN
Author: Mohamed Fazil
Author-email: mohamedfazil463@gmail.com
License: MIT
Keywords: fazil,data structures,psg,dce
Platform: UNKNOWN
Classifier: Development Status :: 5 - Production/Stable
Classifier: Intended Audience :: Education
Classifier: Operating System :: Microsoft :: Windows :: Windows 10
Classifier: License :: OSI Approved :: MIT License
Classifier: Programming Language :: Python :: 3
